setup.py
bin/status.py
ripplepy.egg-info/PKG-INFO
ripplepy.egg-info/SOURCES.txt
ripplepy.egg-info/dependency_links.txt
ripplepy.egg-info/top_level.txt
src/ripplepy/__init__.py
src/ripplepy/ripplepy.py