Metadata-Version: 1.0
Name: ripplepy
Version: 0.1
Summary: RipplePy is a osu!ripple third party API
Home-page: https://github.com/kidJaNateTH/ripplepy
Author: NateTH
Author-email: kidjanate@gmail.com
License: NateTH
Keywords: RipplePy
Platform: UNKNOWN
